<PAMDataset>
  <Metadata>
    <MDI key="DataType">Generic</MDI>
  </Metadata>
  <PAMRasterBand band="1">
    <Histograms>
      <HistItem>
        <HistMin>257</HistMin>
        <HistMax>65535</HistMax>
        <BucketCount>256</BucketCount>
        <IncludeOutOfRange>1</IncludeOutOfRange>
        <Approximate>0</Approximate>
        <HistCounts>11251|3419|3240|3469|3798|4067|4356|4718|5356|5886|6920|7866|9082|10240|11746|13741|15649|18278|21262|24152|27238|30771|34678|37129|39747|41955|43540|45368|46635|48212|49958|51107|52433|54538|56438|57874|58649|60033|60985|62234|63240|64118|64799|66318|67226|67415|68307|68936|69316|70129|69233|70222|69842|69753|69458|69095|68771|68359|68607|68239|68661|68079|68270|66485|68399|69193|68378|68751|69478|69040|69135|68912|68175|67613|67235|67310|68086|68628|69219|69500|71042|72782|74171|74624|72108|76530|78515|78861|80637|82452|85847|90160|94818|100614|106449|112230|119802|125439|132171|137184|139477|140197|143253|141663|138224|132146|127464|123068|120068|115488|113307|110930|108890|106619|104746|101744|99128|94465|89623|84910|79438|73901|69239|64460|59755|56565|53261|44588|47158|43602|41276|39046|36707|35422|33123|31641|30104|28425|26398|24895|22836|21231|20098|18749|17987|16829|16050|15621|15158|14413|13707|13590|12730|12536|12055|11604|11406|10905|10740|10304|10125|9546|8971|8504|8334|8107|7733|7439|7063|6557|6553|6264|6228|5977|6029|5806|5463|5219|4972|4562|4126|3962|3697|3441|3330|3223|2910|2877|2772|2559|2373|2257|2175|2018|1966|1939|1860|1860|1718|1672|1681|1567|1405|1389|1204|1147|1098|1074|970|856|825|798|742|690|671|663|649|627|623|610|604|581|517|543|481|525|416|472|449|439|396|356|325|303|307|237|193|210|158|185|169|161|177|165|195|178|220|222|251|228|241|272|252|326|42|683</HistCounts>
      </HistItem>
    </Histograms>
    <Metadata>
      <MDI key="RepresentationType">ATHEMATIC</MDI>
      <MDI key="STATISTICS_COVARIANCES">85843812.4739601,82516885.81506166,89747659.95286521</MDI>
      <MDI key="STATISTICS_EXCLUDEDVALUES"></MDI>
      <MDI key="STATISTICS_MAXIMUM">65535</MDI>
      <MDI key="STATISTICS_MEAN">22399.839591909</MDI>
      <MDI key="STATISTICS_MEDIAN">23552.286275</MDI>
      <MDI key="STATISTICS_MINIMUM">257</MDI>
      <MDI key="STATISTICS_SKIPFACTORX">1</MDI>
      <MDI key="STATISTICS_SKIPFACTORY">1</MDI>
      <MDI key="STATISTICS_STDDEV">9265.1936015369</MDI>
    </Metadata>
  </PAMRasterBand>
  <PAMRasterBand band="2">
    <Histograms>
      <HistItem>
        <HistMin>0</HistMin>
        <HistMax>65535</HistMax>
        <BucketCount>256</BucketCount>
        <IncludeOutOfRange>1</IncludeOutOfRange>
        <Approximate>0</Approximate>
        <HistCounts>7020|2858|2484|2411|2544|2875|3280|3529|3880|4261|4621|5012|5785|6776|7696|8828|10192|11991|14284|16769|19146|22316|25546|29149|32794|35677|38198|40492|42513|44181|45684|47364|48651|50590|51719|53790|56106|57665|59885|61551|62927|64521|65464|67438|68620|69958|70246|71521|71914|72606|73068|73484|73470|73482|73154|73549|72872|73066|72961|73617|73930|73974|73800|74142|74147|74065|74198|73895|73965|74624|74658|73250|73145|72328|71527|70774|70687|70958|72211|73069|74434|76603|77753|80012|80959|82367|84267|85126|86600|88499|91259|94270|98544|102778|107766|112816|119051|125893|133396|139839|143842|146120|148382|147290|146764|141910|134568|127906|121810|116230|112470|111344|109189|107348|104574|100273|93868|87640|81753|77093|73003|69099|65277|62219|57894|54257|49312|46280|42610|40049|37861|36225|35090|33534|31648|29417|27680|25512|24138|22769|20795|19265|17873|16625|15868|15027|14643|14146|13836|13336|12870|12469|12148|11634|11250|10891|10480|10147|9837|9252|8979|8266|8070|7821|7800|7491|7093|6865|6411|6300|6108|5713|5531|5271|5202|4970|4797|4385|4361|3964|3741|3694|3387|3386|3404|3204|2955|2813|2810|2623|2560|2501|2353|2345|2216|2180|2014|1831|1747|1520|1441|1440|1284|1205|1123|1140|1154|1059|997|945|842|808|734|707|688|624|633|631|570|554|630|603|546|551|504|533|537|543|517|497|464|482|425|442|438|417|372|333|278|314|318|290|320|328|297|288|249|217|172|133|126|120|102|108|124|153</HistCounts>
      </HistItem>
    </Histograms>
    <Metadata>
      <MDI key="RepresentationType">ATHEMATIC</MDI>
      <MDI key="STATISTICS_COVARIANCES">82516885.81506166,80447372.6849504,87646455.12950422</MDI>
      <MDI key="STATISTICS_EXCLUDEDVALUES"></MDI>
      <MDI key="STATISTICS_MAXIMUM">65535</MDI>
      <MDI key="STATISTICS_MEAN">22244.864245805</MDI>
      <MDI key="STATISTICS_MEDIAN">23130.000000</MDI>
      <MDI key="STATISTICS_MINIMUM">0</MDI>
      <MDI key="STATISTICS_SKIPFACTORX">1</MDI>
      <MDI key="STATISTICS_SKIPFACTORY">1</MDI>
      <MDI key="STATISTICS_STDDEV">8969.2459373657</MDI>
    </Metadata>
  </PAMRasterBand>
  <PAMRasterBand band="3">
    <Histograms>
      <HistItem>
        <HistMin>0</HistMin>
        <HistMax>65535</HistMax>
        <BucketCount>256</BucketCount>
        <IncludeOutOfRange>1</IncludeOutOfRange>
        <Approximate>0</Approximate>
        <HistCounts>4750|2199|2567|2427|2701|3034|3300|3715|4222|4741|5493|6328|7310|8546|9800|11238|13017|14961|17335|19365|21449|24149|26136|27946|30356|31880|34202|36148|37881|40031|42128|43341|45518|47334|49032|50728|52497|53835|55881|57126|59259|60251|60643|61912|62713|64136|63973|64562|65266|65107|65275|65013|65313|65444|65239|64659|65591|64552|64519|63138|63079|62661|62479|62288|62083|62438|63317|62417|63126|63056|63180|63381|62875|63617|64471|64402|64809|64640|64169|63866|63680|62801|62794|62605|62282|62505|62655|63554|64552|66200|67815|69416|71370|73209|75325|75894|77478|78687|80872|82093|84023|86516|88945|92288|96754|100624|105021|109432|114059|118575|123128|127364|130871|131765|131973|130678|129684|127384|124684|120649|116332|111618|106488|102129|98407|95402|91692|88485|85054|81335|76644|73072|69428|65612|62369|59169|55786|52366|48886|45434|41959|38585|35923|33149|30868|28320|26817|24631|23324|22154|20693|19578|18269|16847|15704|14577|13429|12814|12204|11586|11364|11104|10896|10635|10508|10334|9646|9617|9124|8839|8531|8129|7694|7422|7163|7096|6782|6714|6381|6247|6326|5959|5899|5492|5147|4826|4673|4527|4388|4240|4114|3765|3499|3302|3379|3154|3202|3037|2957|2789|2667|2657|2587|2504|2349|2235|2070|1948|1729|1680|1682|1560|1455|1400|1387|1288|1229|1209|1095|1032|1018|950|890|892|839|903|811|779|788|734|746|705|657|672|629|534|511|525|475|480|486|438|437|414|424|414|479|426|382|310|309|303|253|302|278|536</HistCounts>
      </HistItem>
    </Histograms>
    <Metadata>
      <MDI key="RepresentationType">ATHEMATIC</MDI>
      <MDI key="STATISTICS_COVARIANCES">89747659.95286521,87646455.12950422,97696780.26266503</MDI>
      <MDI key="STATISTICS_EXCLUDEDVALUES"></MDI>
      <MDI key="STATISTICS_MAXIMUM">65535</MDI>
      <MDI key="STATISTICS_MEAN">23905.184304597</MDI>
      <MDI key="STATISTICS_MEDIAN">25186.000000</MDI>
      <MDI key="STATISTICS_MINIMUM">0</MDI>
      <MDI key="STATISTICS_SKIPFACTORX">1</MDI>
      <MDI key="STATISTICS_SKIPFACTORY">1</MDI>
      <MDI key="STATISTICS_STDDEV">9884.1681624032</MDI>
    </Metadata>
  </PAMRasterBand>
</PAMDataset>
